gitxray/gitxray.py
gitxray/include/__init__.py
gitxray/include/gh_api.py
gitxray/include/gh_public_events.py
gitxray/include/gh_reactions.py
gitxray/include/gh_time.py
gitxray/include/gx_arg_parser.py
gitxray/include/gx_context.py
gitxray/include/gx_definitions.py
gitxray/include/gx_output.py
gitxray/include/gx_ugly_openpgp_parser.py
gitxray/include/gx_ugly_ssh_parser.py
gitxray/include/vt_api.py
gitxray/include/html_report/__init__.py
gitxray/include/html_report/template_contributor.html
gitxray/include/html_report/template_highlights.html
gitxray/include/html_report/template_main.html
gitxray/include/html_report/template_non_contributor.html
gitxray/include/html_report/template_repository.html
gitxray/include/html_report/template_table.html
gitxray/xrays/__init__.py
gitxray/xrays/association_xray.py
gitxray/xrays/contributors_xray.py
gitxray/xrays/repository_xray.py
gitxray/xrays/workflows_xray.py
gitxray-1.0.20.dist-info/METADATA
gitxray-1.0.20.dist-info/WHEEL
gitxray-1.0.20.dist-info/entry_points.txt
gitxray-1.0.20.dist-info/top_level.txt
gitxray-1.0.20.dist-info/RECORD
