Metadata-Version: 2.4
Name: gitxray
Version: 1.0.20
Summary: A multifaceted security tool which leverages Public GitHub REST APIs for OSINT, Forensics, Pentesting and more.
Author-email: Lucas Lavarello <llavarello@kulkan.com>
Project-URL: Homepage, https://github.com/kulkansecurity/gitxray
Project-URL: Issues, https://github.com/kulkansecurity/gitxray/issues
Classifier: Programming Language :: Python :: 3
Classifier: License :: OSI Approved :: GNU Affero General Public License v3
Classifier: Operating System :: OS Independent
Classifier: Topic :: Security
Classifier: Topic :: Utilities
Requires-Python: >=3.8
Requires-Dist: requests>=2.32.3
